ppaas
