Metadata-Version: 1.1
Name: ppaas
Version: 0.0.2
Summary: Interface for OVH's Puppet as a service lab
Home-page: https://github.com/thomas-maurice/puppet-as-a-service-wrapper
Author: Thomas Maurice
Author-email: thomas@maurice.fr
License: WTFPL
Platform: any
Classifier: Development Status :: 3 - Alpha
Classifier: Environment :: Console
Classifier: Intended Audience :: Developers
Classifier: Topic :: Software Development :: Libraries :: Python Modules
Classifier: Programming Language :: Python :: 2.7
